jh_scrapyd/VERSION
jh_scrapyd/__init__.py
jh_scrapyd/__main__.py
jh_scrapyd/app.py
jh_scrapyd/basicauth.py
jh_scrapyd/config.py
jh_scrapyd/default_scrapyd.conf
jh_scrapyd/eggstorage.py
jh_scrapyd/environ.py
jh_scrapyd/exceptions.py
jh_scrapyd/interfaces.py
jh_scrapyd/jobstorage.py
jh_scrapyd/launcher.py
jh_scrapyd/poller.py
jh_scrapyd/runner.py
jh_scrapyd/scheduler.py
jh_scrapyd/spiderqueue.py
jh_scrapyd/sqlite.py
jh_scrapyd/txapp.py
jh_scrapyd/utils.py
jh_scrapyd/webservice.py
jh_scrapyd/website.py
jh_scrapyd/jh/common.py
jh_scrapyd/jh/queue/redis_queue.py
jh_scrapyd/jh/utils/encryption.py
jh_scrapyd-0.3.7.dist-info/METADATA
jh_scrapyd-0.3.7.dist-info/WHEEL
jh_scrapyd-0.3.7.dist-info/entry_points.txt
jh_scrapyd-0.3.7.dist-info/top_level.txt
jh_scrapyd-0.3.7.dist-info/RECORD
