Metadata-Version: 2.1
Name: jh_scrapyd
Version: 0.3.7
Summary: Preemptive scraping cluster
Home-page: https://github.com/mrye5869/jh_scrapyd
Author: Mr Ye
Author-email: mrye5869@gmail.com
License: MIT
Classifier: Development Status :: 4 - Beta
Classifier: Intended Audience :: Developers
Classifier: License :: OSI Approved :: MIT License
Classifier: Programming Language :: Python :: 3
Classifier: Programming Language :: Python :: 3.7
Classifier: Programming Language :: Python :: 3.8
Classifier: Programming Language :: Python :: 3.9
Classifier: Programming Language :: Python :: 3.10
Classifier: Operating System :: OS Independent
Requires-Python: >=3.7
Requires-Dist: Twisted>=20.3.0
Requires-Dist: scrapy>=2.0.0
Requires-Dist: redis>=5.2.1
Requires-Dist: pytz>=2024.2
Requires-Dist: psutil>=6.1.1
Requires-Dist: pywin32; platform_system == "Windows"
Provides-Extra: dev
Requires-Dist: pytest>=6.0.0; extra == "dev"
Requires-Dist: pytest-cov; extra == "dev"
Requires-Dist: flake8; extra == "dev"
Provides-Extra: docs
Requires-Dist: sphinx>=4.0.0; extra == "docs"
Requires-Dist: sphinx_rtd_theme; extra == "docs"
